{"slug":"convert-seconds-to-hours","title":"Convert seconds to hours","trackId":3721,"tags":["C","Java","JavaScript","Kotlin","TypeScript","Python"],"contributors":["joao-vitor-souza","rksp25","astitva0011","jaypavasiya","grraghav120","Robert-Capra","harshraj8843"],"contentHtml":"<h2>Write a program to convert seconds to hours</h2>\n<p>1 hour = 60 minutes = 3600 seconds</p>\n<pre><code>Input  : 18000\r\nOutput : 5\n</code></pre>\n<hr>\n<pre><code>#include &#x3C;stdio.h>\n\nint main() {\n  float hours,sec; \n  //taking input as hours\n  printf(\"How many hours?:\");\n  scanf(\"%f\",&#x26;hours);\n  //converting \n  sec=hours*3600;\n  //Output\n  printf(\"%.2f\",sec);\n\n    return 0;\n}\n</code></pre>\n<pre><code>import java.util.*;\nimport java.io.*;\nimport java.text.*;\npublic class Main\n{\n\tpublic static void main(String[] args) {\n\t    Scanner sc=new Scanner(System.in);\n\t    int n=sc.nextInt();\n\t\tSystem.out.println(n/3600);\n\t}\n}\n\n// Contributed by Raghav Garg (@grraghav120)\n</code></pre>\n<pre><code>function secondsToHMS(d) {\n    d = Number(d);\n    var h = Math.floor(d / 3600);\n    var m = Math.floor(d % 3600 / 60);\n    var s = Math.floor(d % 3600 % 60);\n\n    var hourDisplay = h > 0 ? h + (h === 1 ? \" hour, \" : \" hours, \") : \"\";\n    var minDisplay = m > 0 ? m + (m === 1 ? \" minute, \" : \" minutes, \") : \"\";\n    var secDisplay = s > 0 ? s + (s === 1 ? \" second\" : \" seconds\") : \"\";\n    return hourDisplay + minDisplay + secDisplay; \n}\n\n\nconsole.log(secondsToHMS(18000))\n</code></pre>\n<pre><code>import java.util.Scanner\n\nfun main() {\n    print(\"Enter Seconds : \")\n    println()\n    var sec = readLine()\n\n    println(\"$sec seconds in hours : \" + ConvertSecondsToHours(sec!!.toInt()))\n\n}\n\nprivate fun ConvertSecondsToHours(sec: Int): Int {\n    val hour = sec / 3600;\n\n    return  hour\n}\n</code></pre>\n<pre><code>function secondsToHMS(d: number):string {\n    d = Number(d);\n    var h = Math.floor(d / 3600);\n    var m = Math.floor(d % 3600 / 60);\n    var s = Math.floor(d % 3600 % 60);\n\n    var hourDisplay = h > 0 ? h + (h === 1 ? \" hour, \" : \" hours, \") : \"\";\n    var minDisplay = m > 0 ? m + (m === 1 ? \" minute, \" : \" minutes, \") : \"\";\n    var secDisplay = s > 0 ? s + (s === 1 ? \" second\" : \" seconds\") : \"\";\n    return hourDisplay + minDisplay + secDisplay; \n}\n\n\nconsole.log(secondsToHMS(61))\n</code></pre>\n<pre><code>def convertSecondsToHours(seconds):\n    return seconds / 3600\n\n\nseconds = 18000\nprint(\"Input: \" + str(seconds))\nprint(\"Output: \" + str(convertSecondsToHours(seconds)))\n</code></pre>\n","markdown":"\n## Write a program to convert seconds to hours\n\n1 hour = 60 minutes = 3600 seconds\r\n\r\n```\r\nInput  : 18000\r\nOutput : 5\r\n```\n\n---\n\n<CodeBlock slug=\"convert-seconds-to-hours\" >\n\n```c\n#include <stdio.h>\n\nint main() {\n  float hours,sec; \n  //taking input as hours\n  printf(\"How many hours?:\");\n  scanf(\"%f\",&hours);\n  //converting \n  sec=hours*3600;\n  //Output\n  printf(\"%.2f\",sec);\n\n    return 0;\n}\n```\n\n```java\nimport java.util.*;\nimport java.io.*;\nimport java.text.*;\npublic class Main\n{\n\tpublic static void main(String[] args) {\n\t    Scanner sc=new Scanner(System.in);\n\t    int n=sc.nextInt();\n\t\tSystem.out.println(n/3600);\n\t}\n}\n\n// Contributed by Raghav Garg (@grraghav120)\n```\n\n```js\nfunction secondsToHMS(d) {\n    d = Number(d);\n    var h = Math.floor(d / 3600);\n    var m = Math.floor(d % 3600 / 60);\n    var s = Math.floor(d % 3600 % 60);\n\n    var hourDisplay = h > 0 ? h + (h === 1 ? \" hour, \" : \" hours, \") : \"\";\n    var minDisplay = m > 0 ? m + (m === 1 ? \" minute, \" : \" minutes, \") : \"\";\n    var secDisplay = s > 0 ? s + (s === 1 ? \" second\" : \" seconds\") : \"\";\n    return hourDisplay + minDisplay + secDisplay; \n}\n\n\nconsole.log(secondsToHMS(18000))\n```\n\n```kt\nimport java.util.Scanner\n\nfun main() {\n    print(\"Enter Seconds : \")\n    println()\n    var sec = readLine()\n\n    println(\"$sec seconds in hours : \" + ConvertSecondsToHours(sec!!.toInt()))\n\n}\n\nprivate fun ConvertSecondsToHours(sec: Int): Int {\n    val hour = sec / 3600;\n\n    return  hour\n}\n```\n\n```ts\nfunction secondsToHMS(d: number):string {\n    d = Number(d);\n    var h = Math.floor(d / 3600);\n    var m = Math.floor(d % 3600 / 60);\n    var s = Math.floor(d % 3600 % 60);\n\n    var hourDisplay = h > 0 ? h + (h === 1 ? \" hour, \" : \" hours, \") : \"\";\n    var minDisplay = m > 0 ? m + (m === 1 ? \" minute, \" : \" minutes, \") : \"\";\n    var secDisplay = s > 0 ? s + (s === 1 ? \" second\" : \" seconds\") : \"\";\n    return hourDisplay + minDisplay + secDisplay; \n}\n\n\nconsole.log(secondsToHMS(61))\n```\n\n```py\ndef convertSecondsToHours(seconds):\n    return seconds / 3600\n\n\nseconds = 18000\nprint(\"Input: \" + str(seconds))\nprint(\"Output: \" + str(convertSecondsToHours(seconds)))\n```\n\n</CodeBlock>\n\n","latestUpdateDate":"2022-12-02T06:03:31Z"}