{"slug":"find-volume-of-a-cone","title":"Find volume of a cone","trackId":3871,"tags":["C++","Java","Python"],"contributors":["sanmay321","harshraj8843","castanedadev-edu","Medmly20208"],"contentHtml":"<h2>Write a program to find volume of a cone</h2>\n<p>Volume of cone = 1/3 × π × <code>Radius</code>^2 × <code>Height</code></p>\n<pre><code>Radius : 2\r\nHeight : 3\r\n\r\nVolume : 12.566370614359\n</code></pre>\n<hr>\n<pre><code>#include &#x3C;iostream> \n#include &#x3C;algorithm> \n#include &#x3C;iomanip>\nusing namespace std;  \nint main()  \n{  \n    double Pi = 3.14285714286;  // Pi = π \n    double Radius, Height; \n    cin>>Radius>>Height;   \n    double ans = Pi*(Radius*Radius)*Height/3;\n    cout &#x3C;&#x3C; fixed &#x3C;&#x3C;setprecision(15);\n    cout&#x3C;&#x3C;ans;\n    return 0;  \n}\n</code></pre>\n<pre><code>import java.util.Scanner;\n\npublic class FindVolumeOfACone {\n    public static void main(String[] args) {\n        double radius, height, volume = 0;\n        Scanner sc = new Scanner(System.in);\n\n        do {\n            System.out.print(\"Radius: \");\n            while (!sc.hasNextDouble()) {\n                System.out.print(\"Oops! That's not a number! \\nRadius: \");\n                sc.next();\n            }\n            radius = sc.nextDouble();\n        } while (radius &#x3C;= 0.0d);\n\n        do {\n            System.out.print(\"Height: \");\n            while (!sc.hasNextDouble()) {\n                System.out.print(\"Oops! That's not a number! \\nHeight: \");\n                sc.next();\n            }\n            height = sc.nextDouble();\n        } while (height &#x3C;= 0.0d);\n\n        sc.close();\n\n        volume = Math.PI * Math.pow(radius, 2) * (height / 3);\n\n        System.out.printf(\"\\nVolume : %f\", volume);\n    }\n}\n</code></pre>\n<pre><code>import math\n\n\ndef FindVolumeOfACone(radius: float, height: float) -> float:\n    \"\"\"\n    find volume of a cone\n    Arguments:\n        radius: a float\n        height: a float\n    Returns:\n        The volume of a cone : a float\n    \"\"\"\n\n    return (1 / 3) * math.pi * math.pow(radius, 2) * height\n\n\nif __name__ == \"__main__\":\n    radius = float(input(\"Radius: \"))\n    height = float(input(\"Height: \"))\n    print(\"Volume:\", FindVolumeOfACone(radius, height))\n</code></pre>\n","markdown":"\r\n## Write a program to find volume of a cone\r\n\r\nVolume of cone = 1/3 × π × `Radius`^2 × `Height`\r\n\r\n```\r\nRadius : 2\r\nHeight : 3\r\n\r\nVolume : 12.566370614359\r\n```\r\n\r\n---\n\n<CodeBlock slug=\"find-volume-of-a-cone\" >\n\n```cpp\n#include <iostream> \n#include <algorithm> \n#include <iomanip>\nusing namespace std;  \nint main()  \n{  \n    double Pi = 3.14285714286;  // Pi = π \n    double Radius, Height; \n    cin>>Radius>>Height;   \n    double ans = Pi*(Radius*Radius)*Height/3;\n    cout << fixed <<setprecision(15);\n    cout<<ans;\n    return 0;  \n}\n```\n\n```java\nimport java.util.Scanner;\n\npublic class FindVolumeOfACone {\n    public static void main(String[] args) {\n        double radius, height, volume = 0;\n        Scanner sc = new Scanner(System.in);\n\n        do {\n            System.out.print(\"Radius: \");\n            while (!sc.hasNextDouble()) {\n                System.out.print(\"Oops! That's not a number! \\nRadius: \");\n                sc.next();\n            }\n            radius = sc.nextDouble();\n        } while (radius <= 0.0d);\n\n        do {\n            System.out.print(\"Height: \");\n            while (!sc.hasNextDouble()) {\n                System.out.print(\"Oops! That's not a number! \\nHeight: \");\n                sc.next();\n            }\n            height = sc.nextDouble();\n        } while (height <= 0.0d);\n\n        sc.close();\n\n        volume = Math.PI * Math.pow(radius, 2) * (height / 3);\n\n        System.out.printf(\"\\nVolume : %f\", volume);\n    }\n}\n```\n\n```py\nimport math\n\n\ndef FindVolumeOfACone(radius: float, height: float) -> float:\n    \"\"\"\n    find volume of a cone\n    Arguments:\n        radius: a float\n        height: a float\n    Returns:\n        The volume of a cone : a float\n    \"\"\"\n\n    return (1 / 3) * math.pi * math.pow(radius, 2) * height\n\n\nif __name__ == \"__main__\":\n    radius = float(input(\"Radius: \"))\n    height = float(input(\"Height: \"))\n    print(\"Volume:\", FindVolumeOfACone(radius, height))\n```\n\n</CodeBlock>\n\n","latestUpdateDate":"2022-10-14T09:12:19Z"}